qiskit_quimb/__init__.py
qiskit_quimb/circuit.py
qiskit_quimb/gate.py
qiskit_quimb-0.0.10.dist-info/licenses/LICENSE
qiskit_quimb-0.0.10.dist-info/WHEEL
qiskit_quimb-0.0.10.dist-info/METADATA
qiskit_quimb-0.0.10.dist-info/RECORD
