Metadata-Version: 2.4
Name: qiskit-quimb
Version: 0.0.10
Summary: Simulate Qiskit circuits using quimb
Requires-Python: >=3.9
Classifier: License :: OSI Approved :: Apache Software License
Classifier: Programming Language :: Python
Classifier: Programming Language :: Python :: 3 :: Only
Classifier: Programming Language :: Python :: 3.9
Classifier: Programming Language :: Python :: 3.10
Classifier: Programming Language :: Python :: 3.11
Classifier: Programming Language :: Python :: 3.12
Classifier: Programming Language :: Python :: 3.13
Classifier: Topic :: Scientific/Engineering :: Physics
Classifier: Topic :: Software Development :: Libraries :: Python Modules
License-File: LICENSE
Requires-Dist: qiskit
Requires-Dist: quimb >= 1.11
Requires-Dist: coverage ; extra == "dev"
Requires-Dist: mypy ; extra == "dev"
Requires-Dist: myst-parser ; extra == "dev"
Requires-Dist: nbmake ; extra == "dev"
Requires-Dist: nbsphinx ; extra == "dev"
Requires-Dist: pytest ; extra == "dev"
Requires-Dist: qiskit[visualization] ; extra == "dev"
Requires-Dist: qiskit-sphinx-theme ; extra == "dev"
Requires-Dist: ruff ; extra == "dev"
Requires-Dist: sphinx ; extra == "dev"
Requires-Dist: sphinx-autodoc-typehints ; extra == "dev"
Requires-Dist: kahypar ; extra == "docs"
Project-URL: Homepage, https://github.com/qiskit-community/qiskit-quimb
Provides-Extra: dev
Provides-Extra: docs
